nutaan_erp/__init__.py
nutaan_erp/core/__init__.py
nutaan_erp/core/agent.py
nutaan_erp/core/config.py
nutaan_erp/core/intent_engine.py
nutaan_erp/core/tools.py
nutaan_erp/core/tracker.py
nutaan_erp/integrations/__init__.py
nutaan_erp/integrations/langchain.py
nutaan_erp/utils/__init__.py
nutaan_erp/utils/context.py
nutaan_erp-1.0.3.dist-info/licenses/LICENSE
nutaan_erp-1.0.3.dist-info/METADATA
nutaan_erp-1.0.3.dist-info/WHEEL
nutaan_erp-1.0.3.dist-info/top_level.txt
nutaan_erp-1.0.3.dist-info/RECORD
