Metadata-Version: 2.4
Name: nutaan_erp
Version: 1.0.3
Summary: Nutaan ERP AI Agent SDK - Autonomous AI agent for ERPNext/Frappe with 14 built-in tools
Home-page: https://github.com/tecosys/nutaan-erp
Author: Nutaan AI (Tecosys)
Author-email: "Nutaan AI (Tecosys)" <hara@nutaan.com>
License: MIT
Project-URL: Homepage, https://github.com/tecosys/nutaan-erp
Project-URL: Documentation, https://github.com/tecosys/nutaan-erp
Project-URL: Repository, https://github.com/tecosys/nutaan-erp
Project-URL: Bug Tracker, https://github.com/tecosys/nutaan-erp/issues
Keywords: ai,agent,erp,erpnext,frappe,automation,langchain,gemini
Classifier: Development Status :: 4 - Beta
Classifier: Intended Audience :: Developers
Classifier: License :: OSI Approved :: MIT License
Classifier: Programming Language :: Python :: 3
Classifier: Programming Language :: Python :: 3.8
Classifier: Programming Language :: Python :: 3.9
Classifier: Programming Language :: Python :: 3.10
Classifier: Programming Language :: Python :: 3.11
Classifier: Programming Language :: Python :: 3.12
Classifier: Topic :: Software Development :: Libraries :: Python Modules
Classifier: Topic :: Office/Business
Classifier: Operating System :: OS Independent
Requires-Python: >=3.8
License-File: LICENSE
Requires-Dist: langchain>=0.3.0
Requires-Dist: langchain-google-genai>=2.0.0
Requires-Dist: langchain-core>=0.3.0
Dynamic: author
Dynamic: home-page
Dynamic: license-file
Dynamic: requires-python
